{"data":[{"id":"qPJ5L9lPmK7-1","text":"Hi. My name is Lukas.","type":"sentence","start_time":"00:00:12.720","end_time":"00:00:14.700","unapproved":1,"translation":{"text":"Chào. Tôi tên là Lukas","google_translate":1},"recordStat":{"voice_text":"","voice_audio":"","right":0,"wrong":0}},{"id":"qPJ5L9lPmK7-2","text":"Hi. My name is Lukas as well.","type":"sentence","start_time":"00:00:15.520","end_time":"00:00:17.540","unapproved":1,"translation":{"text":"Chào. Tôi tên là Lukas.","google_translate":1},"recordStat":{"voice_text":"","voice_audio":"","right":0,"wrong":0}},{"id":"qPJ5L9lPmK7-3","text":"And we are teachers.","type":"sentence","start_time":"00:00:18.220","end_time":"00:00:20.660","unapproved":1,"translation":{"text":"Và chúng tôi là giáo viên.","google_translate":1},"recordStat":{"voice_text":"","voice_audio":"","right":0,"wrong":0}},{"id":"qPJ5L9lPmK7-4","text":"We'll start with the dough.","type":"sentence","start_time":"00:00:23.120","end_time":"00:00:26.040","unapproved":1,"translation":{"text":"Chúng ta sẽ bắt đầu với bột.","google_translate":1},"recordStat":{"voice_text":"","voice_audio":"","right":0,"wrong":0}},{"id":"qPJ5L9lPmK7-5","text":"Lukas","type":"sentence","start_time":"00:00:27.240","end_time":"00:00:27.900","unapproved":1,"translation":{"text":"Lukas","google_translate":1},"recordStat":{"voice_text":"","voice_audio":"","right":0,"wrong":0}},{"id":"qPJ5L9lPmK7-6","text":"You pour four hundred grams of flour into the bowl.","type":"sentence","start_time":"00:00:29.300","end_time":"00:00:34.980","unapproved":1,"translation":{"text":"Bạn đổ bốn trăm gram bột vào bát.","google_translate":1},"recordStat":{"voice_text":"","voice_audio":"","right":0,"wrong":0}},{"id":"qPJ5L9lPmK7-7","text":"Now, You mix the yeast with 200 ml of hot water.","type":"sentence","start_time":"00:00:44.560","end_time":"00:00:58.980","unapproved":1,"translation":{"text":"Bây giờ, Bạn trộn men với 200 ml nước nóng.","google_translate":1},"recordStat":{"voice_text":"","voice_audio":"","right":0,"wrong":0}},{"id":"qPJ5L9lPmK7-8","text":"You add a teaspoon of sea salt.","type":"sentence","start_time":"00:01:05.580","end_time":"00:01:11.780","unapproved":1,"translation":{"text":"Bạn thêm một muỗng cà phê muối biển.","google_translate":1},"recordStat":{"voice_text":"","voice_audio":"","right":0,"wrong":0}},{"id":"qPJ5L9lPmK7-9","text":"And now you'll add two teaspoons of olive oil.","type":"sentence","start_time":"00:01:15.420","end_time":"00:01:21.920","unapproved":1,"translation":{"text":"Và bây giờ bạn sẽ thêm hai muỗng cà phê dầu ô liu.","google_translate":1},"recordStat":{"voice_text":"","voice_audio":"","right":0,"wrong":0}},{"id":"qPJ5L9lPmK7-10","text":"Come on!","type":"sentence","start_time":"00:01:25.460","end_time":"00:01:26.460","unapproved":1,"translation":{"text":"Nào!","google_translate":1},"recordStat":{"voice_text":"","voice_audio":"","right":0,"wrong":0}},{"id":"qPJ5L9lPmK7-11","text":"Ok, ok, ok...","type":"sentence","start_time":"00:01:26.740","end_time":"00:01:28.780","unapproved":1,"translation":{"text":"Được được được...","google_translate":1},"recordStat":{"voice_text":"","voice_audio":"","right":0,"wrong":0}},{"id":"qPJ5L9lPmK7-12","text":"It's new, isn't it?","type":"sentence","start_time":"00:01:29.600","end_time":"00:01:32.300","unapproved":1,"translation":{"text":"Nó mới phải không?","google_translate":1},"recordStat":{"voice_text":"","voice_audio":"","right":0,"wrong":0}},{"id":"qPJ5L9lPmK7-13","text":"You pour this mixture into the flour.","type":"sentence","start_time":"00:01:36.040","end_time":"00:01:41.080","unapproved":1,"translation":{"text":"Bạn đổ hỗn hợp này vào bột.","google_translate":1},"recordStat":{"voice_text":"","voice_audio":"","right":0,"wrong":0}},{"id":"qPJ5L9lPmK7-14","text":"Ok.","type":"sentence","start_time":"00:01:41.560","end_time":"00:01:42.200","unapproved":1,"translation":{"text":"Đồng ý.","google_translate":1},"recordStat":{"voice_text":"","voice_audio":"","right":0,"wrong":0}},{"id":"qPJ5L9lPmK7-15","text":"And you prepare the dough.","type":"sentence","start_time":"00:01:55.840","end_time":"00:02:00.340","unapproved":1,"translation":{"text":"Và bạn chuẩn bị bột.","google_translate":1},"recordStat":{"voice_text":"","voice_audio":"","right":0,"wrong":0}},{"id":"qPJ5L9lPmK7-16","text":"You mix the dough for three or four minutes...till it's ready.","type":"sentence","start_time":"00:02:04.160","end_time":"00:02:10.380","unapproved":1,"translation":{"text":"Bạn trộn bột trong ba hoặc bốn phút ... cho đến khi nó sẵn sàng.","google_translate":1},"recordStat":{"voice_text":"","voice_audio":"","right":0,"wrong":0}},{"id":"qPJ5L9lPmK7-17","text":"Good job!","type":"sentence","start_time":"00:02:14.580","end_time":"00:02:16.140","unapproved":1,"translation":{"text":"Làm tốt lắm!","google_translate":1},"recordStat":{"voice_text":"","voice_audio":"","right":0,"wrong":0}},{"id":"qPJ5L9lPmK7-18","text":"We add little flour.","type":"sentence","start_time":"00:02:16.940","end_time":"00:02:19.460","unapproved":1,"translation":{"text":"Chúng tôi thêm ít bột mì.","google_translate":1},"recordStat":{"voice_text":"","voice_audio":"","right":0,"wrong":0}},{"id":"qPJ5L9lPmK7-19","text":"Lukas is almost ready.","type":"sentence","start_time":"00:02:20.160","end_time":"00:02:22.880","unapproved":1,"translation":{"text":"Lukas gần như đã sẵn sàng.","google_translate":1},"recordStat":{"voice_text":"","voice_audio":"","right":0,"wrong":0}},{"id":"qPJ5L9lPmK7-20","text":"Use the rolling pin and make flat cakes.","type":"sentence","start_time":"00:02:29.640","end_time":"00:02:36.880","unapproved":1,"translation":{"text":"Sử dụng pin lăn và làm cho bánh phẳng.","google_translate":1},"recordStat":{"voice_text":"","voice_audio":"","right":0,"wrong":0}},{"id":"qPJ5L9lPmK7-21","text":"...a profesionall, right?","type":"sentence","start_time":"00:02:40.000","end_time":"00:02:43.120","unapproved":1,"translation":{"text":"... một chuyên gia, phải không?","google_translate":1},"recordStat":{"voice_text":"","voice_audio":"","right":0,"wrong":0}},{"id":"qPJ5L9lPmK7-22","text":"What we do now is that we cut the correct","type":"sentence","start_time":"00:02:44.460","end_time":"00:02:50.700","unapproved":1,"translation":{"text":"Những gì chúng tôi làm bây giờ là chúng tôi cắt chính xác","google_translate":1},"recordStat":{"voice_text":"","voice_audio":"","right":0,"wrong":0}},{"id":"qPJ5L9lPmK7-23","text":"Aah, wait a minute!","type":"sentence","start_time":"00:02:50.980","end_time":"00:02:53.080","unapproved":1,"translation":{"text":"Aah, đợi một chút!","google_translate":1},"recordStat":{"voice_text":"","voice_audio":"","right":0,"wrong":0}},{"id":"qPJ5L9lPmK7-24","text":"I have a... special pizza cutter.","type":"sentence","start_time":"00:02:53.320","end_time":"00:02:59.220","unapproved":1,"translation":{"text":"Tôi có một ... máy cắt pizza đặc biệt.","google_translate":1},"recordStat":{"voice_text":"","voice_audio":"","right":0,"wrong":0}},{"id":"qPJ5L9lPmK7-25","text":"Now it's almost done.","type":"sentence","start_time":"00:03:02.100","end_time":"00:03:06.220","unapproved":1,"translation":{"text":"Bây giờ nó đã gần xong.","google_translate":1},"recordStat":{"voice_text":"","voice_audio":"","right":0,"wrong":0}},{"id":"qPJ5L9lPmK7-26","text":"And we lay the perfect circular dough onto the tray.","type":"sentence","start_time":"00:03:08.440","end_time":"00:03:16.820","unapproved":1,"translation":{"text":"Và chúng tôi đặt bột tròn hoàn hảo lên khay.","google_translate":1},"recordStat":{"voice_text":"","voice_audio":"","right":0,"wrong":0}},{"id":"qPJ5L9lPmK7-27","text":"Step No. 2.","type":"sentence","start_time":"00:03:18.900","end_time":"00:03:21.880","unapproved":1,"translation":{"text":"Bước số 2.","google_translate":1},"recordStat":{"voice_text":"","voice_audio":"","right":0,"wrong":0}},{"id":"qPJ5L9lPmK7-28","text":"Dice the onion.","type":"sentence","start_time":"00:03:22.940","end_time":"00:03:25.060","unapproved":1,"translation":{"text":"Xúc xắc hành tây.","google_translate":1},"recordStat":{"voice_text":"","voice_audio":"","right":0,"wrong":0}},{"id":"qPJ5L9lPmK7-29","text":"Ok.","type":"sentence","start_time":"00:03:25.200","end_time":"00:03:25.700","unapproved":1,"translation":{"text":"Đồng ý.","google_translate":1},"recordStat":{"voice_text":"","voice_audio":"","right":0,"wrong":0}},{"id":"qPJ5L9lPmK7-30","text":"Slice the tomato.","type":"sentence","start_time":"00:03:34.920","end_time":"00:03:38.420","unapproved":1,"translation":{"text":"Cắt lát cà chua.","google_translate":1},"recordStat":{"voice_text":"","voice_audio":"","right":0,"wrong":0}},{"id":"qPJ5L9lPmK7-31","text":"Slice?","type":"sentence","start_time":"00:03:40.440","end_time":"00:03:40.940","unapproved":1,"translation":{"text":"Lát cắt?","google_translate":1},"recordStat":{"voice_text":"","voice_audio":"","right":0,"wrong":0}},{"id":"qPJ5L9lPmK7-32","text":"Slice! -Ok!","type":"sentence","start_time":"00:03:41.120","end_time":"00:03:42.920","unapproved":1,"translation":{"text":"Lát! -Đồng ý!","google_translate":1},"recordStat":{"voice_text":"","voice_audio":"","right":0,"wrong":0}},{"id":"qPJ5L9lPmK7-33","text":"Grate the cheese on the grater.","type":"sentence","start_time":"00:03:48.380","end_time":"00:03:50.840","unapproved":1,"translation":{"text":"Nướng phô mai trên vắt.","google_translate":1},"recordStat":{"voice_text":"","voice_audio":"","right":0,"wrong":0}},{"id":"qPJ5L9lPmK7-34","text":"Slice Mozzarella.","type":"sentence","start_time":"00:03:57.460","end_time":"00:03:59.460","unapproved":1,"translation":{"text":"Mozzarella cắt lát.","google_translate":1},"recordStat":{"voice_text":"","voice_audio":"","right":0,"wrong":0}},{"id":"qPJ5L9lPmK7-35","text":"Lukas is laying the tomatoes onto the dough.","type":"sentence","start_time":"00:04:10.560","end_time":"00:04:14.860","unapproved":1,"translation":{"text":"Lukas đang đặt cà chua lên bột.","google_translate":1},"recordStat":{"voice_text":"","voice_audio":"","right":0,"wrong":0}},{"id":"qPJ5L9lPmK7-36","text":"Oregano and basil.","type":"sentence","start_time":"00:04:15.640","end_time":"00:04:19.620","unapproved":1,"translation":{"text":"Oregano và húng quế.","google_translate":1},"recordStat":{"voice_text":"","voice_audio":"","right":0,"wrong":0}},{"id":"qPJ5L9lPmK7-37","text":"Lay the ham onto the pizza.","type":"sentence","start_time":"00:04:21.740","end_time":"00:04:25.720","unapproved":1,"translation":{"text":"Đặt giăm bông lên bánh pizza.","google_translate":1},"recordStat":{"voice_text":"","voice_audio":"","right":0,"wrong":0}},{"id":"qPJ5L9lPmK7-38","text":"Pour the pizza with cheese.","type":"sentence","start_time":"00:04:30.420","end_time":"00:04:33.960","unapproved":1,"translation":{"text":"Đổ pizza với phô mai.","google_translate":1},"recordStat":{"voice_text":"","voice_audio":"","right":0,"wrong":0}},{"id":"qPJ5L9lPmK7-39","text":"Lay spinach on the pizza.","type":"sentence","start_time":"00:04:38.660","end_time":"00:04:41.980","unapproved":1,"translation":{"text":"Đặt rau bina trên bánh pizza.","google_translate":1},"recordStat":{"voice_text":"","voice_audio":"","right":0,"wrong":0}},{"id":"qPJ5L9lPmK7-40","text":"Here you are.","type":"sentence","start_time":"00:04:44.700","end_time":"00:04:45.580","unapproved":1,"translation":{"text":"Của bạn đây.","google_translate":1},"recordStat":{"voice_text":"","voice_audio":"","right":0,"wrong":0}},{"id":"qPJ5L9lPmK7-41","text":"Lay champignons onto the pizza.","type":"sentence","start_time":"00:04:49.100","end_time":"00:04:53.180","unapproved":1,"translation":{"text":"Đặt champignons lên pizza.","google_translate":1},"recordStat":{"voice_text":"","voice_audio":"","right":0,"wrong":0}},{"id":"qPJ5L9lPmK7-42","text":"Switch the oven.","type":"sentence","start_time":"00:05:00.540","end_time":"00:05:03.020","unapproved":1,"translation":{"text":"Chuyển lò nướng.","google_translate":1},"recordStat":{"voice_text":"","voice_audio":"","right":0,"wrong":0}},{"id":"qPJ5L9lPmK7-43","text":"And set the temperature at 250 degrees.","type":"sentence","start_time":"00:05:04.560","end_time":"00:05:15.180","unapproved":1,"translation":{"text":"Và đặt nhiệt độ ở 250 độ.","google_translate":1},"recordStat":{"voice_text":"","voice_audio":"","right":0,"wrong":0}},{"id":"qPJ5L9lPmK7-44","text":"15 minutes and the pizza is ready.","type":"sentence","start_time":"00:05:20.680","end_time":"00:05:24.100","unapproved":1,"translation":{"text":"15 phút và pizza đã sẵn sàng.","google_translate":1},"recordStat":{"voice_text":"","voice_audio":"","right":0,"wrong":0}},{"id":"qPJ5L9lPmK7-45","text":"The pizza is ready.","type":"sentence","start_time":"00:05:39.240","end_time":"00:05:40.520","unapproved":1,"translation":{"text":"Bánh pizza đã sẵn sàng.","google_translate":1},"recordStat":{"voice_text":"","voice_audio":"","right":0,"wrong":0}},{"id":"qPJ5L9lPmK7-46","text":"Let's taste it!","type":"sentence","start_time":"00:05:40.940","end_time":"00:05:42.640","unapproved":1,"translation":{"text":"Hãy nếm thử nhé!","google_translate":1},"recordStat":{"voice_text":"","voice_audio":"","right":0,"wrong":0}}],"view":"1","comment":"0","like":"0","dislike":"0","like_status":0,"is_news_a_minute":0,"slideshow":0,"id":"qPJ5L9lPmK7","url":"https://www.youtube.com/watch?v=5OndR7VICEA","title":"Pizza baking - English vocabulary","thumbnail":"https://i.ytimg.com/vi/5OndR7VICEA/hqdefault.jpg","mp4":0,"comment_id":null,"duration":"00:06:11","is_new":null}